pyats/tcl/__init__.py
pyats/tcl/array.cpython-310-x86_64-linux-gnu.so
pyats/tcl/history.cpython-310-x86_64-linux-gnu.so
pyats/tcl/internal.cpython-310-x86_64-linux-gnu.so
pyats/tcl/interpreter.cpython-310-x86_64-linux-gnu.so
pyats/tcl/keyedlist.cpython-310-x86_64-linux-gnu.so
pyats/tcl/namespace.cpython-310-x86_64-linux-gnu.so
pyats/tcl/q.cpython-310-x86_64-linux-gnu.so
pyats/tcl/tclstr.cpython-310-x86_64-linux-gnu.so
pyats.tcl-25.9.dist-info/METADATA
pyats.tcl-25.9.dist-info/WHEEL
pyats.tcl-25.9.dist-info/top_level.txt
pyats.tcl-25.9.dist-info/RECORD
